LICENSE
README.markdown
arghlog.py
setup.py
arghlog.egg-info/PKG-INFO
arghlog.egg-info/SOURCES.txt
arghlog.egg-info/dependency_links.txt
arghlog.egg-info/top_level.txt
docs/Makefile
docs/conf.py
docs/example.py
docs/guide.rst
docs/index.rst
docs/reference.rst