Metadata-Version: 1.1
Name: arghlog
Version: 0.1dev
Summary: Logging integration for argh commands
Home-page: https://github.com/markpasc/arghlog
Author: Mark Paschal
Author-email: markpasc@markpasc.org
License: UNKNOWN
Platform: UNKNOWN
Requires: argparse
Requires: argh
